annxious-callback/__init__.py
annxious-callback/callback.py
annxious_callback/__init__.py
annxious_callback/callback.py
annxious_callback-0.1.2.dist-info/LICENSE
annxious_callback-0.1.2.dist-info/METADATA
annxious_callback-0.1.2.dist-info/WHEEL
annxious_callback-0.1.2.dist-info/top_level.txt
annxious_callback-0.1.2.dist-info/RECORD
