Metadata-Version: 2.1
Name: annxious-callback
Version: 0.1.2
Summary: Keras callback to connect to ANNxious Telegram bot.
Home-page: https://github.com/vlizanae/annxious-bot
Author: Vicente Lizana
Author-email: v.lizana.e@gmail.com
License: UNKNOWN
Platform: UNKNOWN
Classifier: Programming Language :: Python :: 3
Classifier: License :: OSI Approved :: MIT License
Classifier: Operating System :: OS Independent
